quickdownload/__init__.py
quickdownload/__main__.py
quickdownload/cluster.py
quickdownload/queue_manager.py
quickdownload/streaming.py
quickdownload/throttle.py
quickdownload/torrent_utils.py
quickdownload/utils.py
quickdownload-1.5.0.dist-info/licenses/LICENSE
quickdownload-1.5.0.dist-info/METADATA
quickdownload-1.5.0.dist-info/WHEEL
quickdownload-1.5.0.dist-info/entry_points.txt
quickdownload-1.5.0.dist-info/top_level.txt
quickdownload-1.5.0.dist-info/RECORD
