Metadata-Version: 2.4
Name: quickdownload
Version: 1.5.0
Summary: High-performance parallel file downloader with multi-device cluster support, queue system, bandwidth throttling, and torrent support
Author-email: Nikhil K Singh <nsr.nikhilsingh@gmail.com>
License: MIT
Project-URL: homepage, https://github.com/Nikhil-K-Singh/quickdownload
Keywords: download,parallel,torrent,resume,cli,http,https,magnet,cluster,multi-device,queue,throttling
Classifier: Development Status :: 4 - Beta
Classifier: Intended Audience :: Developers
Classifier: Intended Audience :: End Users/Desktop
Classifier: License :: OSI Approved :: MIT License
Classifier: Operating System :: OS Independent
Classifier: Programming Language :: Python :: 3
Classifier: Programming Language :: Python :: 3.7
Classifier: Programming Language :: Python :: 3.8
Classifier: Programming Language :: Python :: 3.9
Classifier: Programming Language :: Python :: 3.10
Classifier: Programming Language :: Python :: 3.11
Classifier: Topic :: Internet :: WWW/HTTP
Classifier: Topic :: System :: Archiving
Classifier: Topic :: Utilities
Requires-Python: >=3.7
License-File: LICENSE
Requires-Dist: libtorrent==2.0.11
Requires-Dist: requests==2.31.0
Dynamic: license-file
